{
  "country": "malaysia",
  "flag": "\ud83c\uddf2\ud83c\uddfe",
  "generated_at": "2026-06-26T08:07:36.953489",
  "fb_ads": [
    {
      "id": "fb-ad-malaysia-001",
      "country": "malaysia",
      "country_flag": "\ud83c\uddf2\ud83c\uddfe",
      "angle": "free_money",
      "headline": "Government Pays Up to 70% of Your Business Costs",
      "body": "MATRADE MDG: up to RM 300K for export development. Free 60-second scan shows everything you qualify for. No obligation.",
      "cta": "Start Free Scan",
      "image_description": "Clean dark card with big green number showing funding amount in MYR. \ud83c\uddf2\ud83c\uddfe flag subtle in corner. Minimal design, premium feel. Text: 'Up to [AMOUNT]' in bold white.",
      "audience": {
        "name": "Manufacturing SMEs",
        "age": "30-60",
        "industries": [
          "Manufacturing",
          "Automotive",
          "Electronics",
          "Furniture"
        ]
      },
      "budget": "US$10-25/day",
      "language": "English"
    },
    {
      "id": "fb-ad-malaysia-002",
      "country": "malaysia",
      "country_flag": "\ud83c\uddf2\ud83c\uddfe",
      "angle": "pain_point",
      "headline": "Struggling with Export market access?",
      "body": "Government schemes cover this. MITI Industry4WRD: up to RM 1M for factory automation. Free eligibility check \u2014 takes 60 seconds.",
      "cta": "Check Eligibility",
      "image_description": "Professional office/workspace photo in Malaysia. Warm lighting. Overlay semi-transparent dark card with green text: '[SOLUTION]'. Human element, relatable setting.",
      "audience": {
        "name": "Manufacturing SMEs",
        "age": "30-60",
        "industries": [
          "Manufacturing",
          "Automotive",
          "Electronics",
          "Furniture"
        ]
      },
      "budget": "US$10-25/day",
      "language": "English"
    },
    {
      "id": "fb-ad-malaysia-003",
      "country": "malaysia",
      "country_flag": "\ud83c\uddf2\ud83c\uddfe",
      "angle": "fear",
      "headline": "Your Competitors Are Claiming This. Are You?",
      "body": "Your non-Bumi competitors found TERAJU grants you didn't know exist. Free GovFund scan shows what you're missing. 26+ schemes, 1 minute.",
      "cta": "See What You Qualify For",
      "image_description": "Split screen: left side grey/empty, right side green/successful. \ud83c\uddf2\ud83c\uddfe on right. Text: 'Don't Get Left Behind'. Strong contrast, emotional pull.",
      "audience": {
        "name": "Manufacturing SMEs",
        "age": "30-60",
        "industries": [
          "Manufacturing",
          "Automotive",
          "Electronics",
          "Furniture"
        ]
      },
      "budget": "US$10-25/day",
      "language": "English"
    },
    {
      "id": "fb-ad-malaysia-004",
      "country": "malaysia",
      "country_flag": "\ud83c\uddf2\ud83c\uddfe",
      "angle": "social_proof",
      "headline": "Hundreds of Malaysia Businesses Already Scanned",
      "body": "Join them. 8 active Malaysian government schemes. GovFund's AI scans every government scheme. Free eligibility check.",
      "cta": "Scan Now",
      "image_description": "Grid of company logos or profile avatars (generic). Text: 'X,XXX businesses scanned'. \ud83c\uddf2\ud83c\uddfe. Trust-building design. Testimonial-style.",
      "audience": {
        "name": "Manufacturing SMEs",
        "age": "30-60",
        "industries": [
          "Manufacturing",
          "Automotive",
          "Electronics",
          "Furniture"
        ]
      },
      "budget": "US$10-25/day",
      "language": "English"
    },
    {
      "id": "fb-ad-malaysia-005",
      "country": "malaysia",
      "country_flag": "\ud83c\uddf2\ud83c\uddfe",
      "angle": "urgency",
      "headline": "Funding Windows Close. Don't Miss Out.",
      "body": "Government funding for Malaysia businesses doesn't wait. Scan now, apply while funds are available.",
      "cta": "Check Eligibility",
      "image_description": "Calendar or countdown visual. Red accent for urgency. \ud83c\uddf2\ud83c\uddfe subtle. Text: 'Applications Close Soon'. Clean, time-pressure design.",
      "audience": {
        "name": "Manufacturing SMEs",
        "age": "30-60",
        "industries": [
          "Manufacturing",
          "Automotive",
          "Electronics",
          "Furniture"
        ]
      },
      "budget": "US$10-25/day",
      "language": "English"
    }
  ],
  "social_posts": [
    {
      "id": "social-malaysia-001",
      "country": "malaysia",
      "country_flag": "\ud83c\uddf2\ud83c\uddfe",
      "type": "educational",
      "content": "Did you know? MATRADE MDG: up to RM 300K for export development\n\nMost Malaysia business owners miss at least 60% of the government schemes they qualify for.\n\nI built a free tool that scans all 10 government agencies in Malaysia and tells you exactly what you can claim.\n\nTakes 60 seconds. No signup. No spam.\n\nLink in first comment \ud83d\udc47",
      "hashtags": [
        "#GovFund",
        "#BusinessGrants",
        "#SMEfunding",
        "#GovernmentGrants",
        "#Malaysia",
        "#MalaysiaBusiness",
        "#SSM",
        "#MATRADE"
      ],
      "platforms": [
        "Facebook Group",
        "LinkedIn"
      ],
      "language": "English",
      "best_time": "Weekday 8-10 AM or 12-2 PM local time"
    },
    {
      "id": "social-malaysia-002",
      "country": "malaysia",
      "country_flag": "\ud83c\uddf2\ud83c\uddfe",
      "type": "case_study_style",
      "content": "A Malaysia food manufacturer came to us last month. They had NO idea they qualified for 10 different government schemes.\n\nTotal eligible: MYR1.2M+ in grants and tax incentives.\n\nAll found in 60 seconds with our free scan.\n\nDon't leave money on the table. Link below.",
      "hashtags": [
        "#GovFund",
        "#BusinessGrants",
        "#SMEfunding",
        "#GovernmentGrants",
        "#Malaysia",
        "#MalaysiaBusiness",
        "#SSM",
        "#MATRADE"
      ],
      "platforms": [
        "Facebook Group",
        "LinkedIn"
      ],
      "language": "English",
      "best_time": "Weekday 8-10 AM or 12-2 PM local time"
    },
    {
      "id": "social-malaysia-003",
      "country": "malaysia",
      "country_flag": "\ud83c\uddf2\ud83c\uddfe",
      "type": "question_hook",
      "content": "When was the last time you checked what government funding your Malaysia business qualifies for?\n\nIf the answer is 'never' or 'last year' \u2014 you're probably missing out.\n\nSchemes change. New ones launch. Old ones expire.\n\nFree scan takes 60 seconds. Updated daily.\n\nCheck now \ud83d\udc47",
      "hashtags": [
        "#GovFund",
        "#BusinessGrants",
        "#SMEfunding",
        "#GovernmentGrants",
        "#Malaysia",
        "#MalaysiaBusiness",
        "#SSM",
        "#MATRADE"
      ],
      "platforms": [
        "Facebook Group",
        "LinkedIn"
      ],
      "language": "English",
      "best_time": "Weekday 8-10 AM or 12-2 PM local time"
    }
  ],
  "landing_page_copy": {
    "country": "malaysia",
    "flag": "\ud83c\uddf2\ud83c\uddfe",
    "hero_headline": "Government Funding for Your Malaysia Business \u2014 Found in 60 Seconds",
    "hero_subheadline": "GovFund's AI scans all government schemes in Malaysia. Grants, loans, tax incentives, rebates, wage subsidies \u2014 all in one scan.",
    "hero_cta": "Check My Eligibility \u2014 Free",
    "pain_point_section": {
      "headline": "Running a Business in Malaysia Is Expensive",
      "points": [
        "\ud83d\udcb8 Automation/IR 4.0 costs",
        "\ud83d\udcb8 Export market access",
        "\ud83d\udcb8 Halal certification costs",
        "\ud83d\udcb8 SME financing access"
      ]
    },
    "solution_section": {
      "headline": "The Government Has Money for This. We Find It.",
      "points": [
        "\u2705 MATRADE MDG: up to RM 300K for export development",
        "\u2705 MITI Industry4WRD: up to RM 1M for factory automation",
        "\u2705 Halal ecosystem grants \u2014 the world's only dedicated Halal support",
        "\u2705 8 active Malaysian government schemes"
      ]
    },
    "trust_section": {
      "headline": "Why {profile['name']} Businesses Trust GovFund",
      "points": [
        "Covers all 10 government agencies",
        "AI-powered matching \u2014 no human bias, no missed schemes",
        "60-second scan, results instantly",
        "Full application handling available"
      ]
    },
    "faq": [
      {
        "q": "Is GovFund a Malaysia government agency?",
        "a": "No. GovFund is a private consultancy. We are NOT a government agency. We help businesses navigate government schemes."
      },
      {
        "q": "Is the scan really free?",
        "a": "Yes. The eligibility scan is free and takes 60 seconds. Full application support is available through our paid plans."
      },
      {
        "q": "What if I'm not eligible for anything?",
        "a": "The scan will tell you exactly that \u2014 no cost, no obligation. But most businesses qualify for at least 3-5 schemes they didn't know about."
      }
    ],
    "generated_at": "2026-06-26T08:07:36.953486"
  },
  "outreach_script": "Hey everyone \ud83d\udc4b\n\nI built a free tool that scans all government funding schemes in Malaysia and tells you what your business qualifies for.\n\nMATRADE MDG: up to RM 300K for export development\n\nIt covers grants, loans, tax incentives, rebates, wage subsidies \u2014 everything. Takes 60 seconds.\n\nI've been sharing it with Malaysia business owners and the average business qualifies for 8-12 schemes they didn't know existed.\n\nNo catch. No spam. Just a free scan.\n\nDrop a comment if you want the link or DM me directly.\n\n\ud83c\uddf2\ud83c\uddfe \ud83c\uddf2\ud83c\uddfe"
}